profile_reddit_restapi_imp_python_package/__init__.py
profile_reddit_restapi_imp_python_package/constants.py
profile_reddit_restapi_imp_python_package/handler.py
profile_reddit_restapi_imp_python_package/search_reddit.py
profile_reddit_local_restapi_imp_python_package-0.0.11.dist-info/METADATA
profile_reddit_local_restapi_imp_python_package-0.0.11.dist-info/WHEEL
profile_reddit_local_restapi_imp_python_package-0.0.11.dist-info/top_level.txt
profile_reddit_local_restapi_imp_python_package-0.0.11.dist-info/RECORD
