Metadata-Version: 2.1
Name: profile-reddit-local-restapi-imp-python-package
Version: 0.0.11
Summary: PyPI Package for Circles profile-local-reddit-restapi-imp Local/Remote Python
Home-page: https://github.com/circles-zone/profile-local-reddit-restapi-imp-python-package
Author: Circles
Author-email: info@circles.life
Classifier: Programming Language :: Python :: 3
Classifier: License :: Other/Proprietary License
Classifier: Operating System :: OS Independent
Requires-Dist: praw >=7.4.0
Requires-Dist: tqdm >=4.64.1
Requires-Dist: database-without-orm-local >=0.0.11
Requires-Dist: importer-local >=0.0.6
Requires-Dist: logzio-python-handler >=4.1.0
Requires-Dist: profile-local >=0.0.11
Requires-Dist: url-local >=0.0.22
Requires-Dist: python-dotenv >=1.0.0
Requires-Dist: logger-local >=0.0.46
Requires-Dist: entity-type-local >=0.0.13
Requires-Dist: source-data-local >=0.0.3
